fastapi_jwt_auth3/__init__.py
fastapi_jwt_auth3/cli.py
fastapi_jwt_auth3/errors.py
fastapi_jwt_auth3/jwtauth.py
fastapi_jwt_auth3/models.py
fastapi_jwt_auth3-0.3.5.dist-info/METADATA
fastapi_jwt_auth3-0.3.5.dist-info/WHEEL
fastapi_jwt_auth3-0.3.5.dist-info/entry_points.txt
fastapi_jwt_auth3-0.3.5.dist-info/licenses/LICENSE
fastapi_jwt_auth3-0.3.5.dist-info/RECORD
