Metadata-Version: 2.3
Name: fastapi-jwt-auth3
Version: 0.3.5
Summary: JWT authentication in FastAPI with ease
Project-URL: Repository, https://github.com/tistaharahap/fastapi-jwt-auth.git
Project-URL: Issues, https://github.com/tistaharahap/fastapi-jwt-auth/issues
Author-email: Batista Harahap <batista@bango29.com>
License-File: LICENSE
Requires-Python: >=3.9
Requires-Dist: fastapi>=0.111.0
Requires-Dist: jwcrypto>=1.5.6
Requires-Dist: pydantic>=2.7.3
Requires-Dist: pyjwt>=2.8.0
Requires-Dist: pytz>=2024.1
Requires-Dist: typer>=0.12.3
